{
	"Version": 3,
	"Meta": {
		"Duration": 7.967,
		"Fps": 30.0,
		"Loop": true,
		"AreBeziersRestricted": true,
		"CurveCount": 80,
		"TotalSegmentCount": 519,
		"TotalPointCount": 1603,
		"UserDataCount": 0,
		"TotalUserDataSize": 0
	},
	"Curves": [
		{
			"Target": "Parameter",
			"Id": "PARAM_ANGLE_X",
			"Segments": [
				0,
				0,
				1,
				0.478,
				0,
				0.956,
				0,
				1.433,
				0,
				1,
				1.778,
				0,
				2.122,
				0,
				2.467,
				0,
				1,
				2.678,
				0,
				2.889,
				2,
				3.1,
				2,
				1,
				3.556,
				2,
				4.011,
				2,
				4.467,
				2,
				1,
				4.633,
				2,
				4.8,
				8.723,
				4.967,
				10,
				1,
				5.222,
				11.959,
				5.478,
				12,
				5.733,
				12,
				1,
				5.989,
				12,
				6.244,
				12,
				6.5,
				12,
				1,
				6.667,
				12,
				6.833,
				12,
				7,
				12,
				1,
				7.322,
				12,
				7.644,
				0,
				7.967,
				0
			]
		},
		{
			"Target": "Parameter",
			"Id": "PARAM_ANGLE_Y",
			"Segments": [
				0,
				0,
				1,
				0.078,
				0,
				0.156,
				-1,
				0.233,
				-1,
				1,
				0.678,
				-1,
				1.122,
				9,
				1.567,
				9,
				1,
				1.911,
				9,
				2.256,
				9.044,
				2.6,
				8,
				1,
				2.811,
				7.36,
				3.022,
				-19,
				3.233,
				-19,
				1,
				3.422,
				-19,
				3.611,
				-13.82,
				3.8,
				-13.82,
				1,
				4.067,
				-13.82,
				4.333,
				-16,
				4.6,
				-16,
				1,
				4.767,
				-16,
				4.933,
				15,
				5.1,
				15,
				1,
				5.356,
				15,
				5.611,
				-4,
				5.867,
				-4,
				1,
				6.122,
				-4,
				6.378,
				0,
				6.633,
				0,
				1,
				6.756,
				0,
				6.878,
				0,
				7,
				0,
				1,
				7.189,
				0,
				7.378,
				6,
				7.567,
				6,
				1,
				7.7,
				6,
				7.833,
				0,
				7.967,
				0
			]
		},
		{
			"Target": "Parameter",
			"Id": "PARAM_ANGLE_Z",
			"Segments": [
				0,
				0,
				1,
				0.2,
				0,
				0.4,
				3.881,
				0.6,
				6,
				1,
				0.856,
				8.708,
				1.111,
				9,
				1.367,
				9,
				1,
				1.711,
				9,
				2.056,
				9.02,
				2.4,
				8,
				1,
				2.611,
				7.375,
				2.822,
				0,
				3.033,
				0,
				1,
				3.222,
				0,
				3.411,
				0,
				3.6,
				0,
				1,
				3.867,
				0,
				4.133,
				-1,
				4.4,
				-1,
				1,
				4.567,
				-1,
				4.733,
				1.372,
				4.9,
				3,
				1,
				5.156,
				5.496,
				5.411,
				6,
				5.667,
				6,
				1,
				5.922,
				6,
				6.178,
				4,
				6.433,
				4,
				1,
				6.622,
				4,
				6.811,
				4,
				7,
				4,
				1,
				7.156,
				4,
				7.311,
				-4,
				7.467,
				-4,
				1,
				7.633,
				-4,
				7.8,
				0,
				7.967,
				0
			]
		},
		{
			"Target": "Parameter",
			"Id": "PARAM_BODY_ANGLE_X",
			"Segments": [
				0,
				0,
				1,
				0.167,
				0,
				0.333,
				-3.768,
				0.5,
				-4,
				1,
				1.1,
				-4.835,
				1.7,
				-5,
				2.3,
				-5,
				1,
				2.511,
				-5,
				2.722,
				-1,
				2.933,
				-1,
				1,
				3.389,
				-1,
				3.844,
				-1,
				4.3,
				-1,
				1,
				4.467,
				-1,
				4.633,
				3.756,
				4.8,
				5,
				1,
				5.056,
				6.908,
				5.311,
				7,
				5.567,
				7,
				1,
				5.822,
				7,
				6.078,
				6,
				6.333,
				6,
				1,
				6.556,
				6,
				6.778,
				6,
				7,
				6,
				1,
				7.322,
				6,
				7.644,
				0,
				7.967,
				0
			]
		},
		{
			"Target": "Parameter",
			"Id": "PARAM_BODY_ANGLE_Y",
			"Segments": [
				0,
				0,
				1,
				0.5,
				0,
				1,
				2,
				1.5,
				2,
				1,
				1.844,
				2,
				2.189,
				1.994,
				2.533,
				1.443,
				1,
				2.744,
				1.106,
				2.956,
				-1,
				3.167,
				-1,
				1,
				3.356,
				-1,
				3.544,
				0.263,
				3.733,
				0.263,
				1,
				4,
				0.263,
				4.267,
				0,
				4.533,
				0,
				1,
				4.7,
				0,
				4.867,
				0,
				5.033,
				0,
				1,
				5.289,
				0,
				5.544,
				-2,
				5.8,
				-2,
				1,
				6.056,
				-2,
				6.311,
				-1,
				6.567,
				-1,
				1,
				6.711,
				-1,
				6.856,
				-1,
				7,
				-1,
				1,
				7.189,
				-1,
				7.378,
				1,
				7.567,
				1,
				1,
				7.7,
				1,
				7.833,
				0,
				7.967,
				0
			]
		},
		{
			"Target": "Parameter",
			"Id": "PARAM_BODY_ANGLE_Z",
			"Segments": [
				0,
				0,
				1,
				0.422,
				0,
				0.844,
				0.517,
				1.267,
				0.517,
				1,
				1.611,
				0.517,
				1.956,
				0.201,
				2.3,
				0,
				1,
				2.511,
				-0.123,
				2.722,
				-0.11,
				2.933,
				-0.11,
				1,
				3.122,
				-0.11,
				3.311,
				-0.062,
				3.5,
				-0.062,
				1,
				3.767,
				-0.062,
				4.033,
				-0.062,
				4.3,
				-0.062,
				1,
				4.467,
				-0.062,
				4.633,
				-3,
				4.8,
				-3,
				1,
				5.056,
				-3,
				5.311,
				-1,
				5.567,
				-1,
				1,
				5.822,
				-1,
				6.078,
				-2,
				6.333,
				-2,
				1,
				6.556,
				-2,
				6.778,
				-2,
				7,
				-2,
				1,
				7.322,
				-2,
				7.644,
				0,
				7.967,
				0
			]
		},
		{
			"Target": "Parameter",
			"Id": "PARAM_BODY_WEIYI",
			"Segments": [
				0,
				0,
				1,
				0.211,
				0,
				0.422,
				-0.38,
				0.633,
				-0.39,
				1,
				0.889,
				-0.402,
				1.144,
				-0.4,
				1.4,
				-0.4,
				1,
				1.744,
				-0.4,
				2.089,
				-0.402,
				2.433,
				-0.34,
				1,
				2.644,
				-0.302,
				2.856,
				0.23,
				3.067,
				0.23,
				1,
				3.256,
				0.23,
				3.444,
				-0.04,
				3.633,
				-0.04,
				1,
				3.9,
				-0.04,
				4.167,
				0.08,
				4.433,
				0.08,
				1,
				4.6,
				0.08,
				4.767,
				-0.35,
				4.933,
				-0.35,
				1,
				5.189,
				-0.35,
				5.444,
				0.06,
				5.7,
				0.06,
				1,
				5.956,
				0.06,
				6.211,
				-0.07,
				6.467,
				-0.07,
				1,
				6.644,
				-0.07,
				6.822,
				-0.07,
				7,
				-0.07,
				1,
				7.322,
				-0.07,
				7.644,
				0,
				7.967,
				0
			]
		},
		{
			"Target": "Parameter",
			"Id": "PARAM_EYE_L_OPEN",
			"Segments": [
				0,
				1,
				1,
				0.111,
				1,
				0.222,
				1,
				0.333,
				1,
				1,
				0.456,
				1,
				0.578,
				0.77,
				0.7,
				0.77,
				1,
				1.244,
				0.77,
				1.789,
				0.77,
				2.333,
				0.77,
				1,
				2.422,
				0.77,
				2.511,
				0,
				2.6,
				0,
				1,
				2.744,
				0,
				2.889,
				0,
				3.033,
				0,
				1,
				3.133,
				0,
				3.233,
				0.67,
				3.333,
				0.67,
				1,
				3.689,
				0.67,
				4.044,
				0.67,
				4.4,
				0.67,
				1,
				4.5,
				0.67,
				4.6,
				0.89,
				4.7,
				0.89,
				1,
				4.978,
				0.89,
				5.256,
				0.89,
				5.533,
				0.89,
				1,
				5.611,
				0.89,
				5.689,
				0,
				5.767,
				0,
				1,
				5.856,
				0,
				5.944,
				0.89,
				6.033,
				0.89,
				1,
				6.356,
				0.89,
				6.678,
				0.89,
				7,
				0.89,
				1,
				7.089,
				0.89,
				7.178,
				1,
				7.267,
				1,
				1,
				7.5,
				1,
				7.733,
				1,
				7.967,
				1
			]
		},
		{
			"Target": "Parameter",
			"Id": "PARAM_EYE_L_SMILE",
			"Segments": [
				0,
				0,
				1,
				2.333,
				0,
				4.667,
				0,
				7,
				0,
				1,
				7.322,
				0,
				7.644,
				0,
				7.967,
				0
			]
		},
		{
			"Target": "Parameter",
			"Id": "PARAM_EYE_R_OPEN",
			"Segments": [
				0,
				1,
				1,
				0.111,
				1,
				0.222,
				1,
				0.333,
				1,
				1,
				0.456,
				1,
				0.578,
				0.77,
				0.7,
				0.77,
				1,
				1.244,
				0.77,
				1.789,
				0.77,
				2.333,
				0.77,
				1,
				2.422,
				0.77,
				2.511,
				0,
				2.6,
				0,
				1,
				2.744,
				0,
				2.889,
				0,
				3.033,
				0,
				1,
				3.133,
				0,
				3.233,
				0.67,
				3.333,
				0.67,
				1,
				3.689,
				0.67,
				4.044,
				0.67,
				4.4,
				0.67,
				1,
				4.5,
				0.67,
				4.6,
				0.9,
				4.7,
				0.9,
				1,
				4.978,
				0.9,
				5.256,
				0.9,
				5.533,
				0.9,
				1,
				5.611,
				0.9,
				5.689,
				0,
				5.767,
				0,
				1,
				5.856,
				0,
				5.944,
				0.9,
				6.033,
				0.9,
				1,
				6.356,
				0.9,
				6.678,
				0.9,
				7,
				0.9,
				1,
				7.089,
				0.9,
				7.178,
				1,
				7.267,
				1,
				1,
				7.5,
				1,
				7.733,
				1,
				7.967,
				1
			]
		},
		{
			"Target": "Parameter",
			"Id": "PARAM_EYE_R_SMILE",
			"Segments": [
				0,
				0,
				1,
				2.333,
				0,
				4.667,
				0,
				7,
				0,
				1,
				7.322,
				0,
				7.644,
				0,
				7.967,
				0
			]
		},
		{
			"Target": "Parameter",
			"Id": "PARAM_EYE_BALL_X",
			"Segments": [
				0,
				0,
				1,
				0.956,
				0,
				1.911,
				0,
				2.867,
				0,
				1,
				2.978,
				0,
				3.089,
				0.02,
				3.2,
				0.02,
				1,
				3.633,
				0.02,
				4.067,
				0.02,
				4.5,
				0.02,
				1,
				4.589,
				0.02,
				4.678,
				0.28,
				4.767,
				0.28,
				1,
				5.078,
				0.28,
				5.389,
				0.28,
				5.7,
				0.28,
				1,
				5.789,
				0.28,
				5.878,
				-0.1,
				5.967,
				-0.1,
				1,
				6.311,
				-0.1,
				6.656,
				-0.1,
				7,
				-0.1,
				1,
				7.089,
				-0.1,
				7.178,
				0,
				7.267,
				0,
				1,
				7.5,
				0,
				7.733,
				0,
				7.967,
				0
			]
		},
		{
			"Target": "Parameter",
			"Id": "PARAM_EYE_BALL_Y",
			"Segments": [
				0,
				0,
				1,
				0.956,
				0,
				1.911,
				0,
				2.867,
				0,
				1,
				2.978,
				0,
				3.089,
				-0.67,
				3.2,
				-0.67,
				1,
				3.633,
				-0.67,
				4.067,
				-0.67,
				4.5,
				-0.67,
				1,
				4.589,
				-0.67,
				4.678,
				0.63,
				4.767,
				0.63,
				1,
				5.078,
				0.63,
				5.389,
				0.63,
				5.7,
				0.63,
				1,
				5.789,
				0.63,
				5.878,
				-0.25,
				5.967,
				-0.25,
				1,
				6.311,
				-0.25,
				6.656,
				-0.25,
				7,
				-0.25,
				1,
				7.089,
				-0.25,
				7.178,
				0,
				7.267,
				0,
				1,
				7.5,
				0,
				7.733,
				0,
				7.967,
				0
			]
		},
		{
			"Target": "Parameter",
			"Id": "PARAM_YANZHUGAOGUANG",
			"Segments": [
				0,
				0,
				1,
				2.333,
				0,
				4.667,
				0,
				7,
				0,
				1,
				7.322,
				0,
				7.644,
				0,
				7.967,
				0
			]
		},
		{
			"Target": "Parameter",
			"Id": "PARAM_yanzhusuofang",
			"Segments": [
				0,
				0,
				1,
				2.333,
				0,
				4.667,
				0,
				7,
				0,
				1,
				7.322,
				0,
				7.644,
				0,
				7.967,
				0
			]
		},
		{
			"Target": "Parameter",
			"Id": "PARAM_BROW_L_X",
			"Segments": [
				0,
				0,
				1,
				0.111,
				0,
				0.222,
				0,
				0.333,
				0,
				1,
				0.456,
				0,
				0.578,
				0.13,
				0.7,
				0.13,
				1,
				1.244,
				0.13,
				1.789,
				0.13,
				2.333,
				0.13,
				1,
				2.422,
				0.13,
				2.511,
				-0.52,
				2.6,
				-0.52,
				1,
				2.744,
				-0.52,
				2.889,
				-0.52,
				3.033,
				-0.52,
				1,
				3.133,
				-0.52,
				3.233,
				-0.07,
				3.333,
				-0.07,
				1,
				3.689,
				-0.07,
				4.044,
				-0.07,
				4.4,
				-0.07,
				1,
				4.5,
				-0.07,
				4.6,
				0.27,
				4.7,
				0.27,
				1,
				4.978,
				0.27,
				5.256,
				0.27,
				5.533,
				0.27,
				1,
				5.611,
				0.27,
				5.689,
				-0.43,
				5.767,
				-0.43,
				1,
				5.856,
				-0.43,
				5.944,
				0.27,
				6.033,
				0.27,
				1,
				6.356,
				0.27,
				6.678,
				0.27,
				7,
				0.27,
				1,
				7.089,
				0.27,
				7.178,
				0,
				7.267,
				0,
				1,
				7.5,
				0,
				7.733,
				0,
				7.967,
				0
			]
		},
		{
			"Target": "Parameter",
			"Id": "PARAM_BROW_R_X",
			"Segments": [
				0,
				0,
				1,
				0.111,
				0,
				0.222,
				0,
				0.333,
				0,
				1,
				0.456,
				0,
				0.578,
				0.13,
				0.7,
				0.13,
				1,
				1.244,
				0.13,
				1.789,
				0.13,
				2.333,
				0.13,
				1,
				2.422,
				0.13,
				2.511,
				-0.51,
				2.6,
				-0.51,
				1,
				2.744,
				-0.51,
				2.889,
				-0.51,
				3.033,
				-0.51,
				1,
				3.133,
				-0.51,
				3.233,
				-0.05,
				3.333,
				-0.05,
				1,
				3.689,
				-0.05,
				4.044,
				-0.05,
				4.4,
				-0.05,
				1,
				4.5,
				-0.05,
				4.6,
				0.29,
				4.7,
				0.29,
				1,
				4.978,
				0.29,
				5.256,
				0.29,
				5.533,
				0.29,
				1,
				5.611,
				0.29,
				5.689,
				-0.39,
				5.767,
				-0.39,
				1,
				5.856,
				-0.39,
				5.944,
				0.29,
				6.033,
				0.29,
				1,
				6.356,
				0.29,
				6.678,
				0.29,
				7,
				0.29,
				1,
				7.089,
				0.29,
				7.178,
				0,
				7.267,
				0,
				1,
				7.5,
				0,
				7.733,
				0,
				7.967,
				0
			]
		},
		{
			"Target": "Parameter",
			"Id": "PARAM_BROW_L_Y",
			"Segments": [
				0,
				0,
				1,
				1.011,
				0,
				2.022,
				0,
				3.033,
				0,
				1,
				3.133,
				0,
				3.233,
				0,
				3.333,
				0,
				1,
				3.689,
				0,
				4.044,
				0,
				4.4,
				0,
				1,
				4.5,
				0,
				4.6,
				0,
				4.7,
				0,
				1,
				4.978,
				0,
				5.256,
				0,
				5.533,
				0,
				1,
				5.611,
				0,
				5.689,
				0,
				5.767,
				0,
				1,
				5.856,
				0,
				5.944,
				0,
				6.033,
				0,
				1,
				6.356,
				0,
				6.678,
				0,
				7,
				0,
				1,
				7.322,
				0,
				7.644,
				0,
				7.967,
				0
			]
		},
		{
			"Target": "Parameter",
			"Id": "PARAM_BROW_R_Y",
			"Segments": [
				0,
				0,
				1,
				1.011,
				0,
				2.022,
				0,
				3.033,
				0,
				1,
				3.133,
				0,
				3.233,
				0,
				3.333,
				0,
				1,
				3.689,
				0,
				4.044,
				0,
				4.4,
				0,
				1,
				4.5,
				0,
				4.6,
				0,
				4.7,
				0,
				1,
				4.978,
				0,
				5.256,
				0,
				5.533,
				0,
				1,
				5.611,
				0,
				5.689,
				0,
				5.767,
				0,
				1,
				5.856,
				0,
				5.944,
				0,
				6.033,
				0,
				1,
				6.356,
				0,
				6.678,
				0,
				7,
				0,
				1,
				7.322,
				0,
				7.644,
				0,
				7.967,
				0
			]
		},
		{
			"Target": "Parameter",
			"Id": "PARAM_BROW_L_ANGLE",
			"Segments": [
				0,
				0,
				1,
				0.111,
				0,
				0.222,
				0,
				0.333,
				0,
				1,
				0.456,
				0,
				0.578,
				-0.09,
				0.7,
				-0.09,
				1,
				1.244,
				-0.09,
				1.789,
				-0.09,
				2.333,
				-0.09,
				1,
				2.567,
				-0.09,
				2.8,
				-0.09,
				3.033,
				-0.09,
				1,
				3.133,
				-0.09,
				3.233,
				0,
				3.333,
				0,
				1,
				3.689,
				0,
				4.044,
				0,
				4.4,
				0,
				1,
				4.5,
				0,
				4.6,
				-0.14,
				4.7,
				-0.14,
				1,
				4.978,
				-0.14,
				5.256,
				-0.14,
				5.533,
				-0.14,
				1,
				5.611,
				-0.14,
				5.689,
				-0.02,
				5.767,
				-0.02,
				1,
				5.856,
				-0.02,
				5.944,
				-0.14,
				6.033,
				-0.14,
				1,
				6.356,
				-0.14,
				6.678,
				-0.14,
				7,
				-0.14,
				1,
				7.089,
				-0.14,
				7.178,
				0,
				7.267,
				0,
				1,
				7.5,
				0,
				7.733,
				0,
				7.967,
				0
			]
		},
		{
			"Target": "Parameter",
			"Id": "PARAM_BROW_R_ANGLE",
			"Segments": [
				0,
				0,
				1,
				0.111,
				0,
				0.222,
				0,
				0.333,
				0,
				1,
				0.456,
				0,
				0.578,
				-0.05,
				0.7,
				-0.05,
				1,
				1.244,
				-0.05,
				1.789,
				-0.05,
				2.333,
				-0.05,
				1,
				2.567,
				-0.05,
				2.8,
				-0.05,
				3.033,
				-0.05,
				1,
				3.133,
				-0.05,
				3.233,
				-0.05,
				3.333,
				-0.05,
				1,
				3.689,
				-0.05,
				4.044,
				-0.05,
				4.4,
				-0.05,
				1,
				4.5,
				-0.05,
				4.6,
				-0.18,
				4.7,
				-0.18,
				1,
				4.978,
				-0.18,
				5.256,
				-0.18,
				5.533,
				-0.18,
				1,
				5.611,
				-0.18,
				5.689,
				-0.1,
				5.767,
				-0.1,
				1,
				5.856,
				-0.1,
				5.944,
				-0.18,
				6.033,
				-0.18,
				1,
				6.356,
				-0.18,
				6.678,
				-0.18,
				7,
				-0.18,
				1,
				7.089,
				-0.18,
				7.178,
				0,
				7.267,
				0,
				1,
				7.5,
				0,
				7.733,
				0,
				7.967,
				0
			]
		},
		{
			"Target": "Parameter",
			"Id": "PARAM_BROW_L_FORM",
			"Segments": [
				0,
				0,
				1,
				0.111,
				0,
				0.222,
				0,
				0.333,
				0,
				1,
				0.456,
				0,
				0.578,
				0.31,
				0.7,
				0.31,
				1,
				1.244,
				0.31,
				1.789,
				0.31,
				2.333,
				0.31,
				1,
				2.422,
				0.31,
				2.511,
				0.03,
				2.6,
				0.03,
				1,
				2.744,
				0.03,
				2.889,
				0.03,
				3.033,
				0.03,
				1,
				3.133,
				0.03,
				3.233,
				0.25,
				3.333,
				0.25,
				1,
				3.689,
				0.25,
				4.044,
				0.25,
				4.4,
				0.25,
				1,
				4.5,
				0.25,
				4.6,
				0.51,
				4.7,
				0.51,
				1,
				4.978,
				0.51,
				5.256,
				0.51,
				5.533,
				0.51,
				1,
				5.611,
				0.51,
				5.689,
				0.13,
				5.767,
				0.13,
				1,
				5.856,
				0.13,
				5.944,
				0.51,
				6.033,
				0.51,
				1,
				6.356,
				0.51,
				6.678,
				0.51,
				7,
				0.51,
				1,
				7.089,
				0.51,
				7.178,
				0,
				7.267,
				0,
				1,
				7.5,
				0,
				7.733,
				0,
				7.967,
				0
			]
		},
		{
			"Target": "Parameter",
			"Id": "PARAM_BROW_R_FORM",
			"Segments": [
				0,
				0,
				1,
				0.111,
				0,
				0.222,
				0,
				0.333,
				0,
				1,
				0.456,
				0,
				0.578,
				0.32,
				0.7,
				0.32,
				1,
				1.244,
				0.32,
				1.789,
				0.32,
				2.333,
				0.32,
				1,
				2.422,
				0.32,
				2.511,
				0.03,
				2.6,
				0.03,
				1,
				2.744,
				0.03,
				2.889,
				0.03,
				3.033,
				0.03,
				1,
				3.133,
				0.03,
				3.233,
				0.24,
				3.333,
				0.24,
				1,
				3.689,
				0.24,
				4.044,
				0.24,
				4.4,
				0.24,
				1,
				4.5,
				0.24,
				4.6,
				0.52,
				4.7,
				0.52,
				1,
				4.978,
				0.52,
				5.256,
				0.52,
				5.533,
				0.52,
				1,
				5.611,
				0.52,
				5.689,
				0.14,
				5.767,
				0.14,
				1,
				5.856,
				0.14,
				5.944,
				0.52,
				6.033,
				0.52,
				1,
				6.356,
				0.52,
				6.678,
				0.52,
				7,
				0.52,
				1,
				7.089,
				0.52,
				7.178,
				0,
				7.267,
				0,
				1,
				7.5,
				0,
				7.733,
				0,
				7.967,
				0
			]
		},
		{
			"Target": "Parameter",
			"Id": "PARAM_MOUTH_FORM",
			"Segments": [
				0,
				0,
				1,
				2.333,
				0,
				4.667,
				0,
				7,
				0,
				1,
				7.322,
				0,
				7.644,
				0,
				7.967,
				0
			]
		},
		{
			"Target": "Parameter",
			"Id": "PARAM_MOUTH_OPEN_Y",
			"Segments": [
				0,
				0,
				1,
				0.033,
				0,
				0.067,
				0.184,
				0.1,
				0.414,
				1,
				0.133,
				0.61,
				0.167,
				1.009,
				0.2,
				1,
				0,
				0.367,
				1,
				1,
				0.389,
				1.007,
				0.411,
				0.841,
				0.433,
				0.763,
				1,
				0.467,
				0.622,
				0.5,
				0.51,
				0.533,
				0.51,
				1,
				0.567,
				0.481,
				0.6,
				0.965,
				0.633,
				1,
				0,
				0.8,
				1,
				1,
				0.822,
				0.975,
				0.844,
				0.939,
				0.867,
				0.941,
				1,
				0.878,
				0.94,
				0.889,
				0.965,
				0.9,
				0.998,
				3,
				0.933,
				1,
				0,
				1,
				1,
				1,
				1.011,
				0.944,
				1.022,
				1.171,
				1.033,
				0.651,
				1,
				1.044,
				0.343,
				1.056,
				-0.015,
				1.067,
				0,
				1,
				1.111,
				-0.007,
				1.156,
				0.925,
				1.2,
				0.918,
				1,
				1.244,
				0.925,
				1.289,
				0.024,
				1.333,
				0.031,
				1,
				1.356,
				0.039,
				1.378,
				0.533,
				1.4,
				0.541,
				1,
				1.467,
				0.545,
				1.533,
				-0.004,
				1.6,
				0,
				0,
				2.6,
				0,
				1,
				2.611,
				-0.019,
				2.622,
				0.438,
				2.633,
				0.831,
				3,
				2.667,
				1,
				0,
				2.767,
				1,
				1,
				2.8,
				0.945,
				2.833,
				0.546,
				2.867,
				0.58,
				1,
				2.889,
				0.585,
				2.911,
				0.783,
				2.933,
				0.996,
				3,
				2.967,
				1,
				0,
				3,
				1,
				2,
				3.033,
				0.804,
				1,
				3.044,
				0.517,
				3.056,
				0.182,
				3.067,
				0.196,
				1,
				3.078,
				0.184,
				3.089,
				0.465,
				3.1,
				0.706,
				1,
				3.111,
				1.088,
				3.122,
				0.98,
				3.133,
				1,
				1,
				3.144,
				0.945,
				3.156,
				1.147,
				3.167,
				0.784,
				1,
				3.178,
				0.58,
				3.189,
				0.343,
				3.2,
				0.353,
				1,
				3.222,
				0.362,
				3.244,
				0.909,
				3.267,
				0.918,
				1,
				3.311,
				0.921,
				3.356,
				0.435,
				3.4,
				0.439,
				1,
				3.422,
				0.441,
				3.444,
				0.524,
				3.467,
				0.525,
				1,
				3.533,
				0.53,
				3.6,
				-0.004,
				3.667,
				0,
				0,
				4.467,
				0,
				1,
				4.5,
				-0.009,
				4.533,
				0.705,
				4.567,
				1,
				0,
				4.6,
				1,
				2,
				4.633,
				0.922,
				1,
				4.644,
				0.783,
				4.656,
				0.621,
				4.667,
				0.627,
				1,
				4.678,
				0.621,
				4.689,
				0.776,
				4.7,
				0.91,
				3,
				4.733,
				1,
				0,
				4.8,
				1,
				1,
				4.822,
				1.07,
				4.844,
				0.884,
				4.867,
				0.805,
				1,
				4.889,
				0.7,
				4.911,
				0.586,
				4.933,
				0.481,
				1,
				4.978,
				0.273,
				5.022,
				0.091,
				5.067,
				0.094,
				1,
				5.089,
				0.098,
				5.111,
				0.364,
				5.133,
				0.369,
				1,
				5.156,
				0.363,
				5.178,
				0.006,
				5.2,
				0,
				1,
				5.211,
				-0.013,
				5.222,
				0.287,
				5.233,
				0.545,
				1,
				5.244,
				0.79,
				5.256,
				1.143,
				5.267,
				1,
				1,
				5.278,
				0.982,
				5.289,
				1.053,
				5.3,
				0.898,
				1,
				5.311,
				0.807,
				5.322,
				0.701,
				5.333,
				0.706,
				1,
				5.356,
				0.708,
				5.378,
				0.853,
				5.4,
				0.855,
				1,
				5.422,
				0.85,
				5.444,
				0.554,
				5.467,
				0.549,
				1,
				5.489,
				0.552,
				5.511,
				0.757,
				5.533,
				0.761,
				1,
				5.622,
				0.758,
				5.711,
				0.003,
				5.8,
				0,
				0,
				7.933,
				0,
				0,
				7.967,
				0
			]
		},
		{
			"Target": "Parameter",
			"Id": "PARAM_MOUTH_SCLAE",
			"Segments": [
				0,
				0,
				1,
				2.333,
				0,
				4.667,
				0,
				7,
				0,
				1,
				7.322,
				0,
				7.644,
				0,
				7.967,
				0
			]
		},
		{
			"Target": "Parameter",
			"Id": "PARAM_JUJUE",
			"Segments": [
				0,
				0,
				1,
				2.333,
				0,
				4.667,
				0,
				7,
				0,
				1,
				7.322,
				0,
				7.644,
				0,
				7.967,
				0
			]
		},
		{
			"Target": "Parameter",
			"Id": "PARAM_CHEEK",
			"Segments": [
				0,
				0,
				1,
				1.189,
				0,
				2.378,
				0,
				3.567,
				0,
				1,
				3.767,
				0,
				3.967,
				-0.37,
				4.167,
				-0.37,
				1,
				5.111,
				-0.37,
				6.056,
				-0.37,
				7,
				-0.37,
				1,
				7.089,
				-0.37,
				7.178,
				0,
				7.267,
				0,
				1,
				7.5,
				0,
				7.733,
				0,
				7.967,
				0
			]
		},
		{
			"Target": "Parameter",
			"Id": "PARAM_BREATH",
			"Segments": [
				0,
				0,
				1,
				0.422,
				0,
				0.844,
				0.54,
				1.267,
				0.54,
				1,
				1.611,
				0.54,
				1.956,
				0.541,
				2.3,
				0.46,
				1,
				2.511,
				0.411,
				2.722,
				0,
				2.933,
				0,
				1,
				3.122,
				0,
				3.311,
				0.43,
				3.5,
				0.43,
				1,
				3.767,
				0.43,
				4.033,
				0.17,
				4.3,
				0.17,
				1,
				4.467,
				0.17,
				4.633,
				0.6,
				4.8,
				0.6,
				1,
				5.056,
				0.6,
				5.311,
				0.09,
				5.567,
				0.09,
				1,
				5.822,
				0.09,
				6.078,
				0.41,
				6.333,
				0.41,
				1,
				6.556,
				0.41,
				6.778,
				0.41,
				7,
				0.41,
				1,
				7.322,
				0.41,
				7.644,
				0,
				7.967,
				0
			]
		},
		{
			"Target": "Parameter",
			"Id": "PARAM_X_ALL",
			"Segments": [
				0,
				0,
				1,
				0.422,
				0,
				0.844,
				-0.02,
				1.267,
				-0.02,
				1,
				1.611,
				-0.02,
				1.956,
				-0.02,
				2.3,
				-0.02,
				1,
				2.511,
				-0.02,
				2.722,
				0,
				2.933,
				0,
				1,
				3.122,
				0,
				3.311,
				0,
				3.5,
				0,
				1,
				3.767,
				0,
				4.033,
				0,
				4.3,
				0,
				1,
				4.722,
				0,
				5.144,
				-0.01,
				5.567,
				-0.01,
				1,
				5.822,
				-0.01,
				6.078,
				0.01,
				6.333,
				0.01,
				1,
				6.556,
				0.01,
				6.778,
				0.01,
				7,
				0.01,
				1,
				7.322,
				0.01,
				7.644,
				0,
				7.967,
				0
			]
		},
		{
			"Target": "Parameter",
			"Id": "PARAM_Y_ALL",
			"Segments": [
				0,
				0,
				1,
				0.167,
				0,
				0.333,
				0.04,
				0.5,
				0.04,
				1,
				0.756,
				0.04,
				1.011,
				0.04,
				1.267,
				0.04,
				1,
				1.611,
				0.04,
				1.956,
				0.04,
				2.3,
				0.04,
				1,
				2.511,
				0.04,
				2.722,
				0.01,
				2.933,
				0.01,
				1,
				3.122,
				0.01,
				3.311,
				0.01,
				3.5,
				0.01,
				1,
				3.767,
				0.01,
				4.033,
				0.01,
				4.3,
				0.01,
				1,
				4.467,
				0.01,
				4.633,
				0.05,
				4.8,
				0.05,
				1,
				5.056,
				0.05,
				5.311,
				0,
				5.567,
				0,
				1,
				5.822,
				0,
				6.078,
				0.02,
				6.333,
				0.02,
				1,
				6.556,
				0.02,
				6.778,
				0.02,
				7,
				0.02,
				1,
				7.322,
				0.02,
				7.644,
				0,
				7.967,
				0
			]
		},
		{
			"Target": "Parameter",
			"Id": "PARAM_Z_ALL",
			"Segments": [
				0,
				0,
				1,
				0.167,
				0,
				0.333,
				-0.12,
				0.5,
				-0.12,
				1,
				0.756,
				-0.12,
				1.011,
				-0.12,
				1.267,
				-0.12,
				1,
				1.611,
				-0.12,
				1.956,
				-0.12,
				2.3,
				-0.12,
				1,
				2.511,
				-0.12,
				2.722,
				0.06,
				2.933,
				0.06,
				1,
				3.122,
				0.06,
				3.311,
				0.04,
				3.5,
				0.04,
				1,
				3.767,
				0.04,
				4.033,
				0.04,
				4.3,
				0.04,
				1,
				4.722,
				0.04,
				5.144,
				0.04,
				5.567,
				0.04,
				1,
				5.822,
				0.04,
				6.078,
				0.03,
				6.333,
				0.03,
				1,
				6.556,
				0.03,
				6.778,
				0.03,
				7,
				0.03,
				1,
				7.322,
				0.03,
				7.644,
				0,
				7.967,
				0
			]
		},
		{
			"Target": "Parameter",
			"Id": "PARAM_SCALE_ALL",
			"Segments": [
				0,
				0,
				1,
				0.167,
				0,
				0.333,
				-0.03,
				0.5,
				-0.03,
				1,
				0.756,
				-0.03,
				1.011,
				-0.03,
				1.267,
				-0.03,
				1,
				1.611,
				-0.03,
				1.956,
				-0.03,
				2.3,
				-0.03,
				1,
				2.967,
				-0.03,
				3.633,
				-0.03,
				4.3,
				-0.03,
				1,
				4.978,
				-0.03,
				5.656,
				-0.03,
				6.333,
				-0.03,
				1,
				6.556,
				-0.03,
				6.778,
				-0.03,
				7,
				-0.03,
				1,
				7.322,
				-0.03,
				7.644,
				0,
				7.967,
				0
			]
		},
		{
			"Target": "Parameter",
			"Id": "PARAM_ARM_R",
			"Segments": [
				0,
				0,
				1,
				0.2,
				0,
				0.4,
				0.129,
				0.6,
				0.2,
				1,
				0.856,
				0.291,
				1.111,
				0.3,
				1.367,
				0.3,
				1,
				1.711,
				0.3,
				2.056,
				0.27,
				2.4,
				0.27,
				1,
				2.611,
				0.27,
				2.822,
				0.4,
				3.033,
				0.4,
				1,
				3.222,
				0.4,
				3.411,
				0.3,
				3.6,
				0.3,
				1,
				3.867,
				0.3,
				4.133,
				0.345,
				4.4,
				0.345,
				1,
				4.567,
				0.345,
				4.733,
				0,
				4.9,
				0,
				1,
				5.156,
				0,
				5.411,
				0.1,
				5.667,
				0.1,
				1,
				5.922,
				0.1,
				6.178,
				0.041,
				6.433,
				0.041,
				1,
				6.622,
				0.041,
				6.811,
				0.041,
				7,
				0.041,
				1,
				7.144,
				0.041,
				7.289,
				-0.1,
				7.433,
				-0.1,
				1,
				7.611,
				-0.1,
				7.789,
				0,
				7.967,
				0
			]
		},
		{
			"Target": "Parameter",
			"Id": "PARAM_LOWARM_R",
			"Segments": [
				0,
				0,
				1,
				0.111,
				0,
				0.222,
				0.04,
				0.333,
				0.1,
				1,
				0.467,
				0.172,
				0.6,
				0.2,
				0.733,
				0.2,
				1,
				1.333,
				0.2,
				1.933,
				0.1,
				2.533,
				0.1,
				1,
				2.744,
				0.1,
				2.956,
				0.5,
				3.167,
				0.5,
				1,
				3.356,
				0.5,
				3.544,
				0.4,
				3.733,
				0.4,
				1,
				4,
				0.4,
				4.267,
				0.5,
				4.533,
				0.5,
				1,
				4.7,
				0.5,
				4.867,
				0.1,
				5.033,
				0.1,
				1,
				5.289,
				0.1,
				5.544,
				0.3,
				5.8,
				0.3,
				1,
				6.056,
				0.3,
				6.311,
				0.242,
				6.567,
				0.242,
				1,
				6.711,
				0.242,
				6.856,
				0.242,
				7,
				0.242,
				1,
				7.178,
				0.242,
				7.356,
				0,
				7.533,
				0,
				1,
				7.678,
				0,
				7.822,
				0,
				7.967,
				0
			]
		},
		{
			"Target": "Parameter",
			"Id": "PARAM_LOWARM_R_LR",
			"Segments": [
				0,
				0,
				1,
				0.767,
				0,
				1.533,
				0,
				2.3,
				0,
				1,
				2.967,
				0,
				3.633,
				0,
				4.3,
				0,
				1,
				4.978,
				0,
				5.656,
				0,
				6.333,
				0,
				1,
				6.556,
				0,
				6.778,
				0,
				7,
				0,
				1,
				7.322,
				0,
				7.644,
				0,
				7.967,
				0
			]
		},
		{
			"Target": "Parameter",
			"Id": "PARAM_HAND_R",
			"Segments": [
				0,
				0,
				1,
				0.156,
				0,
				0.311,
				-0.03,
				0.467,
				-0.03,
				1,
				0.611,
				-0.03,
				0.756,
				0.382,
				0.9,
				0.4,
				1,
				1.144,
				0.431,
				1.389,
				0.43,
				1.633,
				0.43,
				1,
				1.978,
				0.43,
				2.322,
				0.37,
				2.667,
				0.37,
				1,
				2.878,
				0.37,
				3.089,
				0.46,
				3.3,
				0.46,
				1,
				3.489,
				0.46,
				3.678,
				0.14,
				3.867,
				0.14,
				1,
				4.133,
				0.14,
				4.4,
				0.26,
				4.667,
				0.26,
				1,
				4.833,
				0.26,
				5,
				-0.3,
				5.167,
				-0.3,
				1,
				5.422,
				-0.3,
				5.678,
				0.2,
				5.933,
				0.2,
				1,
				6.189,
				0.2,
				6.444,
				0.06,
				6.7,
				0.06,
				1,
				6.8,
				0.06,
				6.9,
				0.06,
				7,
				0.06,
				1,
				7.211,
				0.06,
				7.422,
				-0.26,
				7.633,
				-0.26,
				1,
				7.744,
				-0.26,
				7.856,
				0,
				7.967,
				0
			]
		},
		{
			"Target": "Parameter",
			"Id": "PARAM_youshou",
			"Segments": [
				0,
				0,
				1,
				0.156,
				0,
				0.311,
				0.011,
				0.467,
				-0.13,
				1,
				0.611,
				-0.261,
				0.756,
				-0.74,
				0.9,
				-0.74,
				1,
				1.489,
				-0.74,
				2.078,
				-0.723,
				2.667,
				-0.65,
				1,
				3.067,
				-0.6,
				3.467,
				-0.476,
				3.867,
				-0.43,
				1,
				4.133,
				-0.399,
				4.4,
				-0.402,
				4.667,
				-0.37,
				1,
				4.833,
				-0.35,
				5,
				0.32,
				5.167,
				0.32,
				1,
				5.422,
				0.32,
				5.678,
				-0.03,
				5.933,
				-0.03,
				1,
				6.189,
				-0.03,
				6.444,
				-0.03,
				6.7,
				-0.03,
				1,
				6.8,
				-0.03,
				6.9,
				-0.03,
				7,
				-0.03,
				1,
				7.322,
				-0.03,
				7.644,
				0,
				7.967,
				0
			]
		},
		{
			"Target": "Parameter",
			"Id": "PARAM_youshangbitoushi",
			"Segments": [
				0,
				0,
				1,
				0.222,
				0,
				0.444,
				0,
				0.667,
				0,
				1,
				0.922,
				0,
				1.178,
				0.1,
				1.433,
				0.1,
				1,
				1.778,
				0.1,
				2.122,
				0.081,
				2.467,
				0.04,
				1,
				2.678,
				0.015,
				2.889,
				0,
				3.1,
				0,
				1,
				3.289,
				0,
				3.478,
				0.09,
				3.667,
				0.09,
				1,
				3.933,
				0.09,
				4.2,
				0.01,
				4.467,
				0.01,
				1,
				4.633,
				0.01,
				4.8,
				0.2,
				4.967,
				0.2,
				1,
				5.222,
				0.2,
				5.478,
				0,
				5.733,
				0,
				1,
				5.989,
				0,
				6.244,
				0,
				6.5,
				0,
				1,
				6.667,
				0,
				6.833,
				0,
				7,
				0,
				1,
				7.322,
				0,
				7.644,
				0,
				7.967,
				0
			]
		},
		{
			"Target": "Parameter",
			"Id": "PARAM_youxiabitoushi",
			"Segments": [
				0,
				0,
				1,
				0.244,
				0,
				0.489,
				0.29,
				0.733,
				0.29,
				1,
				1.333,
				0.29,
				1.933,
				0.29,
				2.533,
				0.29,
				1,
				2.744,
				0.29,
				2.956,
				0.09,
				3.167,
				0.09,
				1,
				3.622,
				0.09,
				4.078,
				0.09,
				4.533,
				0.09,
				1,
				4.7,
				0.09,
				4.867,
				0,
				5.033,
				0,
				1,
				5.544,
				0,
				6.056,
				0,
				6.567,
				0,
				1,
				6.711,
				0,
				6.856,
				0,
				7,
				0,
				1,
				7.322,
				0,
				7.644,
				0,
				7.967,
				0
			]
		},
		{
			"Target": "Parameter",
			"Id": "PARAM_HAND_R_VIS",
			"Segments": [
				0,
				0,
				1,
				0.767,
				0,
				1.533,
				0,
				2.3,
				0,
				1,
				2.967,
				0,
				3.633,
				0,
				4.3,
				0,
				1,
				4.978,
				0,
				5.656,
				0,
				6.333,
				0,
				1,
				6.556,
				0,
				6.778,
				0,
				7,
				0,
				1,
				7.322,
				0,
				7.644,
				0,
				7.967,
				0
			]
		},
		{
			"Target": "Parameter",
			"Id": "PARAM_ARM_R_LAYER",
			"Segments": [
				0,
				0,
				1,
				0.767,
				0,
				1.533,
				0,
				2.3,
				0,
				1,
				2.967,
				0,
				3.633,
				0,
				4.3,
				0,
				1,
				4.978,
				0,
				5.656,
				0,
				6.333,
				0,
				1,
				6.556,
				0,
				6.778,
				0,
				7,
				0,
				1,
				7.322,
				0,
				7.644,
				0,
				7.967,
				0
			]
		},
		{
			"Target": "Parameter",
			"Id": "PARAM_ARM_R_SLEEVE",
			"Segments": [
				0,
				0,
				1,
				0.167,
				0,
				0.333,
				-0.85,
				0.5,
				-0.85,
				1,
				1.1,
				-0.85,
				1.7,
				-0.85,
				2.3,
				-0.85,
				1,
				2.7,
				-0.85,
				3.1,
				-1,
				3.5,
				-1,
				1,
				3.767,
				-1,
				4.033,
				-1,
				4.3,
				-1,
				1,
				4.467,
				-1,
				4.633,
				-0.36,
				4.8,
				-0.36,
				1,
				5.056,
				-0.36,
				5.311,
				-1,
				5.567,
				-1,
				1,
				5.822,
				-1,
				6.078,
				-1,
				6.333,
				-1,
				1,
				6.556,
				-1,
				6.778,
				-1,
				7,
				-1,
				1,
				7.322,
				-1,
				7.644,
				0,
				7.967,
				0
			]
		},
		{
			"Target": "Parameter",
			"Id": "PARAM_miaotexiao",
			"Segments": [
				0,
				0,
				1,
				0.767,
				0,
				1.533,
				0,
				2.3,
				0,
				1,
				2.967,
				0,
				3.633,
				0,
				4.3,
				0,
				1,
				4.978,
				0,
				5.656,
				0,
				6.333,
				0,
				1,
				6.556,
				0,
				6.778,
				0,
				7,
				0,
				1,
				7.322,
				0,
				7.644,
				0,
				7.967,
				0
			]
		},
		{
			"Target": "Parameter",
			"Id": "PARAM_ARM_L",
			"Segments": [
				0,
				0,
				1,
				0.211,
				0,
				0.422,
				-0.058,
				0.633,
				-0.1,
				1,
				1.033,
				-0.18,
				1.433,
				-0.2,
				1.833,
				-0.2,
				1,
				2.222,
				-0.2,
				2.611,
				0.2,
				3,
				0.2,
				1,
				3.389,
				0.2,
				3.778,
				-0.3,
				4.167,
				-0.3,
				1,
				4.633,
				-0.3,
				5.1,
				-0.3,
				5.567,
				-0.2,
				1,
				6,
				-0.107,
				6.433,
				0.1,
				6.867,
				0.1,
				1,
				7.233,
				0.1,
				7.6,
				0,
				7.967,
				0
			]
		},
		{
			"Target": "Parameter",
			"Id": "PARAM_LOWAR_L",
			"Segments": [
				0,
				0,
				1,
				0.211,
				0,
				0.422,
				-0.799,
				0.633,
				-0.9,
				1,
				1.033,
				-1.092,
				1.433,
				-1.1,
				1.833,
				-1.1,
				1,
				2.222,
				-1.1,
				2.611,
				-0.767,
				3,
				-0.5,
				1,
				3.389,
				-0.233,
				3.778,
				-0.2,
				4.167,
				-0.2,
				1,
				4.633,
				-0.2,
				5.1,
				-0.3,
				5.567,
				-0.3,
				1,
				6,
				-0.3,
				6.433,
				0.1,
				6.867,
				0.1,
				1,
				7.233,
				0.1,
				7.6,
				0,
				7.967,
				0
			]
		},
		{
			"Target": "Parameter",
			"Id": "PARAM_LOWARM_L_LR",
			"Segments": [
				0,
				0,
				1,
				2.656,
				0,
				5.311,
				0,
				7.967,
				0
			]
		},
		{
			"Target": "Parameter",
			"Id": "PARAM_HAND_L",
			"Segments": [
				0,
				0,
				1,
				2.656,
				0,
				5.311,
				0,
				7.967,
				0
			]
		},
		{
			"Target": "Parameter",
			"Id": "PARAM_zuoshou",
			"Segments": [
				0,
				0,
				1,
				0.289,
				0,
				0.578,
				-0.1,
				0.867,
				-0.1,
				1,
				1.222,
				-0.1,
				1.578,
				-0.1,
				1.933,
				-0.1,
				1,
				2.233,
				-0.1,
				2.533,
				0.1,
				2.833,
				0.1,
				1,
				3.278,
				0.1,
				3.722,
				-0.2,
				4.167,
				-0.2,
				1,
				4.711,
				-0.2,
				5.256,
				0.1,
				5.8,
				0.1,
				1,
				6.256,
				0.1,
				6.711,
				-0.1,
				7.167,
				-0.1,
				1,
				7.433,
				-0.1,
				7.7,
				0,
				7.967,
				0
			]
		},
		{
			"Target": "Parameter",
			"Id": "PARAM_zuoshangbitoushi",
			"Segments": [
				0,
				0,
				1,
				2.656,
				0,
				5.311,
				0,
				7.967,
				0
			]
		},
		{
			"Target": "Parameter",
			"Id": "PARAM_zuoxiaobitoushi",
			"Segments": [
				0,
				0,
				1,
				2.656,
				0,
				5.311,
				0,
				7.967,
				0
			]
		},
		{
			"Target": "Parameter",
			"Id": "PARAM_HAND_L_VIS",
			"Segments": [
				0,
				0,
				1,
				2.656,
				0,
				5.311,
				0,
				7.967,
				0
			]
		},
		{
			"Target": "Parameter",
			"Id": "PARAM_ARM_L_LAYER",
			"Segments": [
				0,
				0,
				1,
				2.656,
				0,
				5.311,
				0,
				7.967,
				0
			]
		},
		{
			"Target": "Parameter",
			"Id": "PARAM_ARM_L_SLEEVE",
			"Segments": [
				0,
				0,
				1,
				2.656,
				0,
				5.311,
				0,
				7.967,
				0
			]
		},
		{
			"Target": "Parameter",
			"Id": "PARAM_RUYAO_X",
			"Segments": [
				0,
				0,
				1,
				2.333,
				0,
				4.667,
				0,
				7,
				0,
				1,
				7.322,
				0,
				7.644,
				0,
				7.967,
				0
			]
		},
		{
			"Target": "Parameter",
			"Id": "PARAM_RUYAO_Y",
			"Segments": [
				0,
				0,
				1,
				2.333,
				0,
				4.667,
				0,
				7,
				0,
				1,
				7.322,
				0,
				7.644,
				0,
				7.967,
				0
			]
		},
		{
			"Target": "Parameter",
			"Id": "PARAM_HUDIEJIE_ROTATE_X",
			"Segments": [
				0,
				0,
				1,
				2.333,
				0,
				4.667,
				0,
				7,
				0,
				1,
				7.322,
				0,
				7.644,
				0,
				7.967,
				0
			]
		},
		{
			"Target": "Parameter",
			"Id": "PARAM_HUDIEJIE_ROTATEY",
			"Segments": [
				0,
				0,
				1,
				2.333,
				0,
				4.667,
				0,
				7,
				0,
				1,
				7.322,
				0,
				7.644,
				0,
				7.967,
				0
			]
		},
		{
			"Target": "Parameter",
			"Id": "PARAM_HUDIEJIE1",
			"Segments": [
				0,
				0,
				1,
				2.333,
				0,
				4.667,
				0,
				7,
				0,
				1,
				7.322,
				0,
				7.644,
				0,
				7.967,
				0
			]
		},
		{
			"Target": "Parameter",
			"Id": "PARAM_HUDIEJIE2",
			"Segments": [
				0,
				0,
				1,
				2.333,
				0,
				4.667,
				0,
				7,
				0,
				1,
				7.322,
				0,
				7.644,
				0,
				7.967,
				0
			]
		},
		{
			"Target": "Parameter",
			"Id": "PARAM_HAIR_FRONT",
			"Segments": [
				0,
				0,
				1,
				2.333,
				0,
				4.667,
				0,
				7,
				0,
				1,
				7.322,
				0,
				7.644,
				0,
				7.967,
				0
			]
		},
		{
			"Target": "Parameter",
			"Id": "PARAM_HAIR_SIDE",
			"Segments": [
				0,
				0,
				1,
				2.333,
				0,
				4.667,
				0,
				7,
				0,
				1,
				7.322,
				0,
				7.644,
				0,
				7.967,
				0
			]
		},
		{
			"Target": "Parameter",
			"Id": "PARAM_HAIR_BACK",
			"Segments": [
				0,
				0,
				1,
				2.333,
				0,
				4.667,
				0,
				7,
				0,
				1,
				7.322,
				0,
				7.644,
				0,
				7.967,
				0
			]
		},
		{
			"Target": "Parameter",
			"Id": "PARAM_HAIR_1_1",
			"Segments": [
				0,
				0,
				1,
				2.333,
				0,
				4.667,
				0,
				7,
				0,
				1,
				7.322,
				0,
				7.644,
				0,
				7.967,
				0
			]
		},
		{
			"Target": "Parameter",
			"Id": "PARAM_HAIR_1_2",
			"Segments": [
				0,
				0,
				1,
				2.333,
				0,
				4.667,
				0,
				7,
				0,
				1,
				7.322,
				0,
				7.644,
				0,
				7.967,
				0
			]
		},
		{
			"Target": "Parameter",
			"Id": "PARAM_HAIR_2_1",
			"Segments": [
				0,
				0,
				1,
				2.333,
				0,
				4.667,
				0,
				7,
				0,
				1,
				7.322,
				0,
				7.644,
				0,
				7.967,
				0
			]
		},
		{
			"Target": "Parameter",
			"Id": "PARAM_HAIR_2_2",
			"Segments": [
				0,
				0,
				1,
				2.333,
				0,
				4.667,
				0,
				7,
				0,
				1,
				7.322,
				0,
				7.644,
				0,
				7.967,
				0
			]
		},
		{
			"Target": "Parameter",
			"Id": "PARAM_Effect01",
			"Segments": [
				0,
				0,
				1,
				2.333,
				0,
				4.667,
				0,
				7,
				0,
				1,
				7.322,
				0,
				7.644,
				0,
				7.967,
				0
			]
		},
		{
			"Target": "Parameter",
			"Id": "PARAM_Effect02",
			"Segments": [
				0,
				0,
				1,
				2.333,
				0,
				4.667,
				0,
				7,
				0,
				1,
				7.322,
				0,
				7.644,
				0,
				7.967,
				0
			]
		},
		{
			"Target": "Parameter",
			"Id": "PARAM_Effect03",
			"Segments": [
				0,
				0,
				1,
				2.333,
				0,
				4.667,
				0,
				7,
				0,
				1,
				7.322,
				0,
				7.644,
				0,
				7.967,
				0
			]
		},
		{
			"Target": "Parameter",
			"Id": "PARAM_Effect04",
			"Segments": [
				0,
				0,
				1,
				2.333,
				0,
				4.667,
				0,
				7,
				0,
				1,
				7.322,
				0,
				7.644,
				0,
				7.967,
				0
			]
		},
		{
			"Target": "Parameter",
			"Id": "PARAM_Effect05",
			"Segments": [
				0,
				0,
				1,
				2.333,
				0,
				4.667,
				0,
				7,
				0,
				1,
				7.322,
				0,
				7.644,
				0,
				7.967,
				0
			]
		},
		{
			"Target": "Parameter",
			"Id": "PARAM_Effect06",
			"Segments": [
				0,
				0,
				1,
				2.333,
				0,
				4.667,
				0,
				7,
				0,
				1,
				7.322,
				0,
				7.644,
				0,
				7.967,
				0
			]
		},
		{
			"Target": "Parameter",
			"Id": "PARAM_Effect07",
			"Segments": [
				0,
				0,
				1,
				2.333,
				0,
				4.667,
				0,
				7,
				0,
				1,
				7.322,
				0,
				7.644,
				0,
				7.967,
				0
			]
		},
		{
			"Target": "Parameter",
			"Id": "PARAM_Effect08",
			"Segments": [
				0,
				0,
				1,
				2.333,
				0,
				4.667,
				0,
				7,
				0,
				1,
				7.322,
				0,
				7.644,
				0,
				7.967,
				0
			]
		},
		{
			"Target": "Parameter",
			"Id": "PARAM_Effect09",
			"Segments": [
				0,
				0,
				1,
				2.333,
				0,
				4.667,
				0,
				7,
				0,
				1,
				7.322,
				0,
				7.644,
				0,
				7.967,
				0
			]
		},
		{
			"Target": "Parameter",
			"Id": "PARAM_Effect10",
			"Segments": [
				0,
				0,
				1,
				2.333,
				0,
				4.667,
				0,
				7,
				0,
				1,
				7.322,
				0,
				7.644,
				0,
				7.967,
				0
			]
		},
		{
			"Target": "Parameter",
			"Id": "PARAM_Effect11",
			"Segments": [
				0,
				0,
				1,
				2.333,
				0,
				4.667,
				0,
				7,
				0,
				1,
				7.322,
				0,
				7.644,
				0,
				7.967,
				0
			]
		},
		{
			"Target": "Parameter",
			"Id": "PARAM_Effect12",
			"Segments": [
				0,
				0,
				1,
				2.333,
				0,
				4.667,
				0,
				7,
				0,
				1,
				7.322,
				0,
				7.644,
				0,
				7.967,
				0
			]
		},
		{
			"Target": "Parameter",
			"Id": "PARAM_Effect13",
			"Segments": [
				0,
				0,
				1,
				2.333,
				0,
				4.667,
				0,
				7,
				0,
				1,
				7.322,
				0,
				7.644,
				0,
				7.967,
				0
			]
		}
	]
}