{"skeleton":{"hash":"ZlFoScpc/ZPsI6b1eEhQhrQUZw8","spine":"2.1.27","width":0,"height":0,"images":""},"bones":[{"name":"root"},{"name":"bone","parent":"root"},{"name":"bone6","parent":"root"},{"name":"bone10","parent":"bone6"},{"name":"bone2","parent":"bone"},{"name":"bone3","parent":"bone"},{"name":"bone4","parent":"bone"},{"name":"bone5","parent":"bone"},{"name":"bone7","parent":"bone6"},{"name":"bone8","parent":"bone6"},{"name":"bone9","parent":"bone6"}],"slots":[{"name":"images/yun1","bone":"bone2"},{"name":"images/yun5","bone":"bone7"},{"name":"images/yun2","bone":"bone3"},{"name":"images/yun6","bone":"bone8"},{"name":"images/yun3","bone":"bone4"},{"name":"images/yun7","bone":"bone9"},{"name":"images/yun4","bone":"bone5"},{"name":"images/yun8","bone":"bone10"}],"skins":{"default":{"images/yun1":{"images/yun1":{"width":669,"height":211}},"images/yun2":{"images/yun2":{"width":788,"height":149}},"images/yun3":{"images/yun3":{"width":916,"height":103}},"images/yun4":{"images/yun4":{"width":800,"height":140}},"images/yun5":{"images/yun1":{"width":669,"height":211}},"images/yun6":{"images/yun2":{"width":788,"height":149}},"images/yun7":{"images/yun3":{"width":916,"height":103}},"images/yun8":{"images/yun4":{"width":800,"height":140}}}},"animations":{"animation":{"slots":{"images/yun1":{"attachment":[{"time":0,"name":"images/yun1"}]},"images/yun2":{"attachment":[{"time":0,"name":"images/yun2"}]},"images/yun3":{"attachment":[{"time":0,"name":"images/yun3"}]},"images/yun4":{"attachment":[{"time":0,"name":"images/yun4"}]},"images/yun5":{"attachment":[{"time":0,"name":"images/yun1"}]},"images/yun6":{"attachment":[{"time":0,"name":"images/yun2"}]},"images/yun7":{"attachment":[{"time":0,"name":"images/yun3"}]},"images/yun8":{"attachment":[{"time":0,"name":"images/yun4"}]}},"bones":{"bone2":{"translate":[{"time":0,"x":-1051.03,"y":372}]},"bone3":{"translate":[{"time":0,"x":-584.64,"y":258.85}]},"bone4":{"translate":[{"time":0,"x":-270,"y":426.21}]},"bone5":{"translate":[{"time":0,"x":162.89,"y":386.04}],"scale":[{"time":0,"x":1.3,"y":1.3}]},"bone":{"translate":[{"time":0,"x":1.21,"y":0},{"time":43.3333,"x":-2228.95,"y":0}]},"bone7":{"translate":[{"time":0,"x":-1051.03,"y":372}]},"bone8":{"translate":[{"time":0,"x":-584.64,"y":258.85}]},"bone9":{"translate":[{"time":0,"x":-270,"y":426.21}]},"bone10":{"translate":[{"time":0,"x":162.89,"y":386.04}],"scale":[{"time":0,"x":1.3,"y":1.3}]},"bone6":{"translate":[{"time":0,"x":2222.97,"y":0},{"time":43.3333,"x":-7.18,"y":0}]}}}}}